Workbook

Sheet ENEL
A1: Consolidado | B1: 40543 | C1: 40908 | D1: 41274 | E1: 41639 | F1: 42004 | G1: 42369 | H1: 42735 | I1: 43100 | J1: 43465 | K1: 43830 | L1: 44196 | M1: 44561 | N1: 44926 | O1: 45291 | P1: 45382
A2: ACTIVO
A3: Activo total | B3: 1489274149 | C3: 1558014006 | D3: 1695255205 | E3: 2256949998 | F3: 3035795403 | G3: 3262953316 | H3: 3480439534 | I3: 3529040173 | J3: 3964215271 | K3: 5169493602 | L3: 4888444532 | M3: 5418228373 | N3: 5595346439 | O3: 5698687722 | P3: 5998205421
A4: Activo Corriente | B4: 379676583 | C4: 365735174 | D4: 422837752 | E4: 568284929 | F4: 881440823 | G4: 694263548 | H4: 767898036 | I4: 744945928 | J4: 810596112 | K4: 1350183140 | L4: 1376958931 | M4: 1297379813 | N4: 1484646595 | O4: 1596064579 | P4: 1578145345
A5: Total de activos corrientes distintos de los activo o grupos de activos para su disposicion clasificados como mantenidos para la venta o como mantenidos para distribuir a los propietarios | B5: 379676583 | C5: 365735174 | D5: 422837752 | E5: 568284929 | F5: 881440823 | G5: 694263548 | H5: 767898036 | I5: 744945928 | J5: 810596112 | K5: 1316112040 | L5: 1362814034 | M5: 1297379813 | N5: 1358940312 | O5: 1592123674 | P5: 1573337275
A6: Efectivo | B6: 75272215 | C6: 23064067 | D6: 53876890 | E6: 19250402 | F6: 378919376 | G6: 136492472 | H6: 110914830 | I6: 145646465 | J6: 72748250 | K6: 447411760 | L6: 202481237 | M6: 108604768 | N6: 186542396 | O6: 530862387 | P6: 284520869
A7: Otros activos financieros corrientes | B7: 870798 | C7: 5407220 | D7: 1277781 | E7: 15429775 | F7: 13146216 | G7: 23819813 | H7: 4765731 | I7: 2118672 | J7: 17161830 | K7: 162710301 | L7: 389290088 | M7: 326830155 | N7: 167147402 | O7: 170887333 | P7: 372506338
A8: Otros activos no financieros corrientes | B8: 13145025 | C8: 16754397 | D8: 15893854 | E8: 20280834 | F8: 28790192 | G8: 27519924 | H8: 28565561 | I8: 33994053 | J8: 108926269 | K8: 88438713 | L8: 85956936 | M8: 95306980 | N8: 108416636 | O8: 126041006 | P8: 125675223
A9: Cuentas por cobrar corrientes | B9: 236011842 | C9: 251229640 | D9: 276768958 | E9: 326740821 | F9: 300591179 | G9: 308517488 | H9: 330626210 | I9: 346455962 | J9: 438739769 | K9: 508571105 | L9: 489258436 | M9: 620457323 | N9: 645453025 | O9: 633257358 | P9: 642310192
A10: Cuentas por cobrar a entidades relacionadas, corrientes | B10: 469192 | C10: 722752 | D10: 379554 | E10: 521772 | F10: 492035 | G10: 698417 | H10: 971320 | I10: 414501 | J10: 389434 | K10: 464522 | L10: 294621 | M10: 210440 | N10: 696046 | O10: 628381 | P10: 405008
A11: Inventarios corrientes | B11: 36799196 | C11: 63091800 | D11: 66357874 | E11: 150457167 | F11: 107121667 | G11: 94434998 | H11: 91416726 | I11: 96928834 | J11: 120229703 | K11: 82615111 | L11: 77736315 | M11: 121126311 | N11: 120441247 | O11: 107545480 | P11: 121357956
A12: Activos por impuestos corrientes, corrientes | B12: 17108315 | C12: 5465298 | D12: 8282841 | E12: 35604158 | F12: 52380158 | G12: 102780436 | H12: 200637658 | I12: 119387441 | J12: 52400857 | K12: 25900528 | L12: 117796401 | M12: 24843836 | N12: 130243560 | O12: 22901729 | P12: 26561689
A13: Activos no corrientes o grupos de activos para su disposicion clasificados como mantenidos para la venta o como mantenidos para distribuir a los propietarios | B13: 0 | C13: 0 | D13: 0 | E13: 0 | F13: 0 | G13: 0 | H13: 0 | I13: 0 | J13: 0 | K13: 34071100 | L13: 14144897 | M13: 0 | N13: 125706283 | O13: 3940905 | P13: 4808070
A14: Activo no Corriente | B14: 1109597566 | C14: 1192278832 | D14: 1272417453 | E14: 1688665069 | F14: 2154354580 | G14: 2568689768 | H14: 2712541498 | I14: 2784094245 | J14: 3153619159 | K14: 3819310462 | L14: 3511485601 | M14: 4120848560 | N14: 4110699844 | O14: 4102623143 | P14: 4420060076
... A25: Propiedad de inversion | B25: 0 | C25: 0 | D25: 0 | E25: 0 | F25: 0 | G25: 0 | H25: 0 | I25: 0 | J25: 0 | K25: 0 | L25: 0 | M25: 0 | N25: 0 | O25: 0 | P25: 0
A26: Activos por derechos de uso | B26: - | C26: 0 | D26: 0 | E26: 0 | F26: 0 | G26: 0 | H26: 0 | I26: 0 | J26: 0 | K26: 0 | L26: 362410839 | M26: 442122455 | N26: 472818691 | O26: 485851073 | P26: 504591654
A27: Activos por impuestos corrientes, no corrientes | B27: 0 | C27: 0 | D27: 0 | E27: 0 | F27: 0 | G27: 0 | H27: 0 | I27: 111376114 | J27: 2366841 | K27: 995171 | L27: 1078992 | M27: 640498 | N27: 1593767 | O27: 0 | P27: 0
A28: Activos por impuestos diferidos | B28: 39853167 | C28: 42866597 | D28: 65408124 | E28: 159987349 | F28: 238069845 | G28: 332969737 | H28: 384574176 | I28: 402576318 | J28: 494804455 | K28: 682381758 | L28: 634767525 | M28: 688472867 | N28: 823241988 | O28: 730737943 | P28: 781805301
A29: Total activos servicios bancarios | B29: 0 | C29: 0 | D29: 0 | E29: 0 | F29: 0 | G29: 0 | H29: 0 | I29: 0 | J29: 0 | K29: 0 | L29: 0 | M29: 0 | N29: 0 | O29: 0 | P29: 0
A31: PASIVO
A32: Pasivo + patrimonio neto | B32: 1489274149 | C32: 1558014006 | D32: 1695255205 | E32: 2256949998 | F32: 3035795403 | G32: 3262953316 | H32: 3480439534 | I32: 3529040173 | J32: 3964215271 | K32: 5169493602 | L32: 4888444532 | M32: 5418228373 | N32: 5595346439 | O32: 5698687722 | P32: 5998205421
A33: Pasivo total | B33: 767899626 | C33: 784936915 | D33: 881248684 | E33: 1375864886 | F33: 2079450541 | G33: 2307606436 | H33: 2218566793 | I33: 2290689003 | J33: 2597793309 | K33: 3560819204 | L33: 3379954105 | M33: 3915183006 | N33: 4040830663 | O33: 4023234762 | P33: 4190615794
A34: Pasivo Corriente | B34: 376371289 | C34: 394261450 | D34: 439322720 | E34: 515270360 | F34: 586386773 | G34: 585028258 | H34: 576051414 | I34: 623404767 | J34: 658742932 | K34: 891001450 | L34: 814156775 | M34: 1159502396 | N34: 1132020070 | O34: 1336992696 | P34: 1341385602
A35: Total de pasivos corrientes distintos de los pasivos incluidos en grupos de activos para su disposicion clasificados como mantenidos para la venta | B35: 376371289 | C35: 394261450 | D35: 439322720 | E35: 515270360 | F35: 586386773 | G35: 585028258 | H35: 576051414 | I35: 623404767 | J35: 658742932 | K35: 891001450 | L35: 814156775 | M35: 1159502396 | N35: 1132020070 | O35: 1336992696 | P35: 1341385602
A36: Otros pasivos financieros corrientes | B36: 14570686 | C36: 18584041 | D36: 28047529 | E36: 27243106 | F36: 20772473 | G36: 21736406 | H36: 24867284 | I36: 36540044 | J36: 20617883 | K36: 28813909 | L36: 22733634 | M36: 196857268 | N36: 275135592 | O36: 337854552 | P36: 333701865
A37: Pasivos por arrendamientos a corto plazo | B37: - | C37: 0 | D37: 0 | E37: 0 | F37: 0 | G37: 0 | H37: 0 | I37: 0 | J37: 0 | K37: 0 | L37: 75453147 | M37: 105314134 | N37: 109048285 | O37: 120979892 | P37: 126171946
A38: Provedores corrientes | B38: 319275469 | C38: 326224772 | D38: 373510494 | E38: 466529349 | F38: 529009412 | G38: 525128910 | H38: 505044060 | I38: 545150721 | J38: 553734579 | K38: 729338168 | L38: 662449107 | M38: 746239147 | N38: 694816615 | O38: 791220467 | P38: 756695389
A39: Cuentas por pagar a entidades relacionadas, corrientes | B39: 0 | C39: 0 | D39: 0 | E39: 0 | F39: 0 | G39: 0 | H39: 0 | I39: 0 | J39: 298309 | K39: 170385 | L39: 332181 | M39: 607794 | N39: 813773 | O39: 2509437 | P39: 3064738
A40: Otras provisiones a corto plazo | B40: 689270 | C40: 578262 | D40: 1635708 | E40: 153974 | F40: 180492 | G40: 3435395 | H40: 5161827 | I40: 7369584 | J40: 8446048 | K40: 1841742 | L40: 1479547 | M40: 1539643 | N40: 2111012 | O40: 3837218 | P40: 5138266
A41: Pasivos por impuestos corrientes, corrientes | B41: 201105 | C41: 7951010 | D41: 5718341 | E41: 1346165 | F41: 12866595 | G41: 5992038 | H41: 4869489 | I41: 355884 | J41: 43407612 | K41: 99275308 | L41: 14700058 | M41: 57204467 | N41: 15177415 | O41: 46692235 | P41: 82905491
A42: Provisiones corrientes por beneficios a los empleados | B42: 0 | C42: 0 | D42: 0 | E42: 0 | F42: 0 | G42: 0 | H42: 0 | I42: 0 | J42: 0 | K42: 0 | L42: 0 | M42: 0 | N42: 0 | O42: 0 | P42: 0
A43: Otros pasivos no financieros corrientes | B43: 41634759 | C43: 40923365 | D43: 30410648 | E43: 19997766 | F43: 23557801 | G43: 28735509 | H43: 36108754 | I43: 33988534 | J43: 32238501 | K43: 31561938 | L43: 37009101 | M43: 51739943 | N43: 34917378 | O43: 33898895 | P43: 33707907
A44: Pasivos incluidos en grupos de activos para su disposicion clasificados como mantenidos para la venta | B44: 0 | C44: 0 | D44: 0 | E44: 0 | F44: 0 | G44: 0 | H44: 0 | I44: 0 | J44: 0 | K44: 0 | L44: 0 | M44: 0 | N44: 0 | O44: 0 | P44: 0
A45: Pasivo no Corriente | B45: 391528337 | C45: 390675465 | D45: 441925964 | E45: 860594526 | F45: 1493063768 | G45: 1722578178 | H45: 1642515379 | I45: 1667284236 | J45: 1939050377 | K45: 2669817754 | L45: 2565797330 | M45: 2755680610 | N45: 2908810593 | O45: 2686242066 | P45: 2849230192
A46: Otros pasivos financieros no corrientes | B46: 350331042 | C46: 353504014 | D46: 407736898 | E46: 813151112 | F46: 1434258466 | G46: 1654135122 | H46: 1576910775 | I46: 1590913982 | J46: 1794895669 | K46: 1969001930 | L46: 1856453965 | M46: 1935510606 | N46: 1945802091 | O46: 1775723807 | P46: 1910809618
A47: Pasivos por arrendamientos a largo plazo | B47: - | C47: 0 | D47: 0 | E47: 0 | F47: 0 | G47: 0 | H47: 0 | I47: 0 | J47: 0 | K47: 0 | L47: 428773709 | M47: 486102565 | N47: 500043082 | O47: 471903079 | P47: 487983377
A48: Acreedores comerciales y otras cuentas a pagar no corrientes | B48: 0 | C48: 0 | D48: 0 | E48: 0 | F48: 0 | G48: 0 | H48: 0 | I48: 0 | J48: 0 | K48: 432945770 | L48: 0 | M48: 0 | N48: 0 | O48: 0 | P48: 0
A49: Cuentas por pagar a entidades relacionadas, no corrientes | B49: 0 | C49: 0 | D49: 0 | E49: 0 | F49: 0 | G49: 0 | H49: 0 | I49: 0 | J49: 0 | K49: 0 | L49: 0 | M49: 0 | N49: 0 | O49: 0 | P49: 0
A50: Otras provisiones a largo plazo | B50: 4001616 | C50: 5123356 | D50: 5869233 | E50: 13370970 | F50: 19596432 | G50: 28582453 | H50: 34222292 | I50: 36481730 | J50: 44054481 | K50: 37285161 | L50: 37718865 | M50: 40770581 | N50: 47636807 | O50: 53255027 | P50: 55674624
A51: Pasivo por impuestos diferidos | B51: 21345618 | C51: 11708289 | D51: 9093058 | E51: 19859855 | F51: 19989741 | G51: 19922788 | H51: 17821387 | I51: 22032668 | J51: 82345876 | K51: 204507336 | L51: 210225420 | M51: 260925087 | N51: 379612964 | O51: 179801727 | P51: 191799156
A52: Pasivos por impuestos corrientes, no corrientes | B52: 0 | C52: 0 | D52: 0 | E52: 0 | F52: 0 | G52: 0 | H52: 0 | I52: 0 | J52: 0 | K52: 0 | L52: 0 | M52: 0 | N52: 0 | O52: 0 | P52: 0
A53: Provisiones no corrientes por beneficios a los empleados | B53: 8257812 | C53: 7718074 | D53: 8007302 | E53: 7862489 | F53: 10226233 | G53: 9496303 | H53: 10407369 | I53: 12171468 | J53: 13189192 | K53: 15045267 | L53: 16071303 | M53: 14731566 | N53: 17094154 | O53: 14856299 | P53: 15213011
A54: Otros pasivos no financieros no corrientes | B54: 7592249 | C54: 12621732 | D54: 11219473 | E54: 6350100 | F54: 8992896 | G54: 10441512 | H54: 3153556 | I54: 5684388 | J54: 4565159 | K54: 11032290 | L54: 16554068 | M54: 17640205 | N54: 18621495 | O54: 190702127 | P54: 187750406
A55: Total pasivos servicios bancarios | B55: 0 | C55: 0 | D55: 0 | E55: 0 | F55: 0 | G55: 0 | H55: 0 | I55: 0 | J55: 0 | K55: 0 | L55: 0 | M55: 0 | N55: 0 | O55: 0 | P55: 0
A56: Patrimonio neto consolidado | B56: 721374523 | C56: 773077091 | D56: 814006521 | E56: 881085112 | F56: 956344862 | G56: 955346880 | H56: 1261872741 | I56: 1238351170 | J56: 1366421962 | K56: 1608674398 | L56: 1508490427 | M56: 1503045367 | N56: 1554515776 | O56: 1675452960 | P56: 1807589627
A57: Patrimonio neto (participacion controladora) | B57: 721374523 | C57: 773077091 | D57: 814006521 | E57: 881085112 | F57: 956344862 | G57: 955346880 | H57: 1261872741 | I57: 1238351170 | J57: 1366421962 | K57: 1608674398 | L57: 1508490427 | M57: 1503045367 | N57: 1554515776 | O57: 1675452960 | P57: 1807589627
A58: Capital emitido | B58: 522667566 | C58: 522667566 | D58: 522667566 | E58: 522667566 | F58: 522667566 | G58: 522667566 | H58: 874846615 | I58: 874846615 | J58: 874846615 | K58: 874846615 | L58: 874846615 | M58: 874846615 | N58: 874846615 | O58: 874846615 | P58: 874846615
A59: Ganancias (perdidas) acumuladas | B59: 289688261 | C59: 310971879 | D59: 351037106 | E59: 415404634 | F59: 435949779 | G59: 426805977 | H59: 450716647 | I59: 481082173 | J59: 557981776 | K59: 665888250 | L59: 724749620 | M59: 549179854 | N59: 653958559 | O59: 687788006 | P59: 667356489
... A64: Participaciones no controladoras | B64: 0 | C64: 0 | D64: 0 | E64: 0 | F64: 0 | G64: 0 | H64: 0 | I64: 0 | J64: 0 | K64: 0 | L64: 0 | M64: 0 | N64: 0 | O64: 0 | P64: 0
A66: EST RESULT
A67: Meses | B67: 12 | C67: 12 | D67: 12 | E67: 12 | F67: 12 | G67: 12 | H67: 12 | I67: 12 | J67: 12 | K67: 12 | L67: 12 | M67: 12 | N67: 12 | O67: 12 | P67: 3
A69: +Ingresos netos | B69: 1083595141 | C69: 1230798252 | D69: 1430115702 | E69: 1628375505 | F69: 1643267385 | G69: 1784612663 | H69: 1867697070 | I69: 1943071198 | J69: 1913174282 | K69: 1978791988 | L69: 2092644232 | M69: 2427220678 | N69: 2540682904 | O69: 2473692310 | P69: 649744559
A70: -Costo de ventas | B70: - | C70: - | D70: - | E70: - | F70: - | G70: - | H70: - | I70: - | J70: - | K70: - | L70: - | M70: - | N70: - | O70: - | P70: -
A71: =Ganancia bruta | B71: - | C71: - | D71: - | E71: - | F71: - | G71: - | H71: - | I71: - | J71: - | K71: - | L71: - | M71: - | N71: - | O71: - | P71: -
A72: +Otros ingresos | B72: - | C72: - | D72: - | E72: - | F72: - | G72: - | H72: - | I72: - | J72: - | K72: - | L72: - | M72: - | N72: - | O72: - | P72: -
A73: -Costos de distribucion | B73: - | C73: - | D73: - | E73: - | F73: - | G73: - | H73: - | I73: - | J73: - | K73: - | L73: - | M73: - | N73: - | O73: - | P73: -
A74: -Gastos de administracion | B74: - | C74: - | D74: - | E74: - | F74: - | G74: - | H74: - | I74: - | J74: - | K74: - | L74: - | M74: - | N74: - | O74: - | P74: -
A75: -Otros gastos, por funcion | B75: - | C75: - | D75: - | E75: - | F75: - | G75: - | H75: - | I75: - | J75: - | K75: - | L75: - | M75: - | N75: - | O75: - | P75: -
A76: +Otras ganancias (perdidas) | B76: -1493117 | C76: -1456948 | D76: -122644 | E76: 2433477 | F76: 5981586 | G76: -33432 | H76: 390536 | I76: 124569 | J76: -89000 | K76: 207275453 | L76: 41585368 | M76: 20809511 | N76: 544963983 | O76: 51324376 | P76: -116948
A77: =Ganancias (perdidas) de actividades operacionales EBIT | B77: 208540723 | C77: 238227340 | D77: 221580037 | E77: 218036930 | F77: 126769297 | G77: 80843799 | H77: 114395321 | I77: 117385336 | J77: 90913071 | K77: 343916569 | L77: 212469036 | M77: 294374685 | N77: 757608676 | O77: 249569340 | P77: 51836701
A78: +Ganancias (perdidas) que surgen de la baja en cuentas de activos financieros medidos al costo amortizado | B78: 0 | C78: 0 | D78: 0 | E78: 0 | F78: 0 | G78: 0 | H78: 0 | I78: 0 | J78: 0 | K78: 0 | L78: 0 | M78: 0 | N78: 0 | O78: 0 | P78: 0
A79: +Ingresos financieros | B79: 970282 | C79: 3059293 | D79: 2823225 | E79: 1946886 | F79: 10818705 | G79: 12183865 | H79: 5952920 | I79: 5225532 | J79: 1889772 | K79: 8746947 | L79: 10894534 | M79: 4919952 | N79: 26563887 | O79: 26535094 | P79: 11361421
A80: -Costos financieros | B80: 9900811 | C80: 10315663 | D80: 13700677 | E80: 20838218 | F80: 55252785 | G80: 70978326 | H80: 82221963 | I80: 80035968 | J80: 77711185 | K80: 97558997 | L80: 102535938 | M80: 113951133 | N80: 113696383 | O80: 113270200 | P80: 27500891
A81: +Deterioro de valor de ganancias y reversion de perdidas por deterioro de valor (perdidas por deterioro de valor) determinado de acuerdo con la NIIF 9 | B81: - | C81: 0 | D81: 0 | E81: 0 | F81: 0 | G81: 0 | H81: 0 | I81: 0 | J81: 0 | K81: 0 | L81: 0 | M81: 0 | N81: 0 | O81: 0 | P81: 0
A82: +Participacion en las ganancias (perdidas) de asociadas y negocios conjuntos que se contabilicen utilizando el metodo de la participacion | B82: 0 | C82: 0 | D82: 0 | E82: 0 | F82: 0 | G82: 0 | H82: 0 | I82: 0 | J82: 0 | K82: 0 | L82: 0 | M82: 0 | N82: 0 | O82: 0 | P82: 0
A83: +Diferencias de cambio | B83: 1296277 | C83: -6349377 | D83: -8795595 | E83: -21078202 | F83: -11243068 | G83: -12945839 | H83: -16051379 | I83: -6973571 | J83: -994222 | K83: 4551310 | L83: -115094 | M83: 250185 | N83: -350491 | O83: -3187775 | P83: -1343755
A84: +Resultados por unidades de reajuste | B84: -3337075 | C84: -5295078 | D84: -3270641 | E84: -1150441 | F84: -22635632 | G84: -22985872 | H84: -15934835 | I84: -9600405 | J84: -16368412 | K84: -19445992 | L84: -26758482 | M84: -66963329 | N84: -130374245 | O84: -39051828 | P84: -5147068
A85: +Ganancias (perdidas) que surgen de diferencias entre importes en libros anteriores y el valor razonable de activos financieros reclasificados como medidos al valor razonable | B85: 0 | C85: 0 | D85: 0 | E85: 0 | F85: 0 | G85: 0 | H85: 0 | I85: 0 | J85: 0 | K85: 0 | L85: 0 | M85: 0 | N85: 0 | O85: 0 | P85: 0
A86: +Gan (perd) acum anteriormente recon en otro res integral que surge de la reclas de act fin de la categoria de medicion de vl raz con cambios en otro res int a la de vl raz con cambios en res | B86: - | C86: 0 | D86: 0 | E86: 0 | F86: 0 | G86: 0 | H86: 0 | I86: 0 | J86: 0 | K86: 0 | L86: 0 | M86: 0 | N86: 0 | O86: 0 | P86: 0
A87: +Ganancias (perdidas) de cobertura por cobertura de un grupo de partidas con posiciones de riesgo compensadoras | B87: - | C87: 0 | D87: 0 | E87: 0 | F87: 0 | G87: 0 | H87: 0 | I87: 0 | J87: 0 | K87: 0 | L87: 0 | M87: 0 | N87: 0 | O87: 0 | P87: 0
A88: =Ganancia (perdida), antes de impuestos | B88: 197569396 | C88: 219326515 | D88: 198636349 | E88: 176916955 | F88: 48456517 | G88: -13882373 | H88: 6140064 | I88: 26000924 | J88: -2270976 | K88: 240209837 | L88: 93954056 | M88: 118630360 | N88: 539751444 | O88: 120594631 | P88: 29206408
A89: -Gasto por impuestos a las ganancias | B89: 24598187 | C89: 38559856 | D89: 31342233 | E89: 29951701 | F89: -8013985 | G89: -12780376 | H89: -28018036 | I89: -17408617 | J89: 21343116 | K89: 86057731 | L89: 9487808 | M89: 43655049 | N89: 82964112 | O89: 31710265 | P89: 49637925
A90: =Ganancia (perdida) procedente de operaciones continuadas | B90: 172971209 | C90: 180766659 | D90: 167294116 | E90: 146965254 | F90: 56470502 | G90: -1101997 | H90: 34158100 | I90: 43409541 | J90: -23614092 | K90: 154152106 | L90: 84466248 | M90: 74975311 | N90: 456787332 | O90: 88884366 | P90: -20431517
A91: -Ganancia (perdida) procedente de operaciones discontinuadas | B91: 0 | C91: 0 | D91: 0 | E91: 0 | F91: 0 | G91: 0 | H91: 0 | I91: 0 | J91: 0 | K91: 0 | L91: 0 | M91: 0 | N91: 0 | O91: 0 | P91: 0
A92: +Ganancia (perdida) neta servicios bancarios | B92: 0 | C92: 0 | D92: 0 | E92: 0 | F92: 0 | G92: 0 | H92: 0 | I92: 0 | J92: 0 | K92: 0 | L92: 0 | M92: 0 | N92: 0 | O92: 0 | P92: 0
A93: =Utilidad consolidada | B93: 172971209 | C93: 180766659 | D93: 167294116 | E93: 146965254 | F93: 56470502 | G93: -1101997 | H93: 34158100 | I93: 43409541 | J93: -23614092 | K93: 154152106 | L93: 84466248 | M93: 74975311 | N93: 456787332 | O93: 88884366 | P93: -20431517
A94: -Ganancia (perdida), atribuible a participaciones no controladoras | B94: 0 | C94: 0 | D94: 0 | E94: 0 | F94: 0 | G94: 0 | H94: 0 | I94: 0 | J94: 0 | K94: 0 | L94: 0 | M94: 0 | N94: 0 | O94: 0 | P94: 0
A95: =Ganancia (perdida) neta | B95: 172971209 | C95: 180766659 | D95: 167294116 | E95: 146965254 | F95: 56470502 | G95: -1101997 | H95: 34158100 | I95: 43409541 | J95: -23614092 | K95: 154152106 | L95: 84466248 | M95: 74975311 | N95: 456787332 | O95: 88884366 | P95: -20431517
A97: EST RESULT
A98: Meses | B98: 12 | C98: 12 | D98: 12 | E98: 12 | F98: 12 | G98: 12 | H98: 12 | I98: 12 | J98: 12 | K98: 12 | L98: 12 | M98: 12 | N98: 12 | O98: 12 | P98: 3
A100: +Ingresos netos | B100: 1083595141 | C100: 1230798252 | D100: 1430115702 | E100: 1628375505 | F100: 1643267385 | G100: 1784612663 | H100: 1867697070 | I100: 1943071198 | J100: 1913174282 | K100: 1978791988 | L100: 2092644232 | M100: 2427220678 | N100: 2540682904 | O100: 2473692310 | P100: 649744559
A101: +Otros ingresos | B101: 4714165 | C101: 11572942 | D101: 10985282 | E101: 13120675 | F101: 18802748 | G101: 8284735 | H101: 19214192 | I101: 11974824 | J101: 9874347 | K101: 11475402 | L101: 13254828 | M101: 12089212 | N101: 52062685 | O101: 48125237 | P101: 15015756
A102: -Disminucion (aumento) en inventarios de productos terminados y en proceso | B102: 0 | C102: 0 | D102: 0 | E102: 0 | F102: 0 | G102: 0 | H102: 0 | I102: 0 | J102: 0 | K102: 0 | L102: 0 | M102: 0 | N102: 0 | O102: 0 | P102: -
A103: +Otros trabajos realizados por la entidad y capitalizados | B103: 0 | C103: 0 | D103: 0 | E103: 0 | F103: 0 | G103: 0 | H103: 0 | I103: 0 | J103: 0 | K103: 0 | L103: 0 | M103: 0 | N103: 0 | O103: 0 | P103: -
A104: -Materias primas y consumibles utilizados | B104: 0 | C104: 0 | D104: 0 | E104: 0 | F104: 0 | G104: 0 | H104: 0 | I104: 0 | J104: 0 | K104: 0 | L104: 0 | M104: 0 | N104: 0 | O104: 0 | P104: -
A105: -Gastos por beneficios a los empleados | B105: 112125960 | C105: 125278220 | D105: 141753518 | E105: 172318252 | F105: 222224875 | G105: 247005733 | H105: 245606059 | I105: 249163558 | J105: 260153627 | K105: 260168138 | L105: 256582135 | M105: 257334487 | N105: 296125852 | O105: 301943147 | P105: 77056052
A106: -Depreciacion y amortizacion | B106: 233199472 | C106: 269798674 | D106: 310069999 | E106: 245165943 | F106: 239635274 | G106: 273625473 | H106: 299584314 | I106: 315867652 | J106: 331565828 | K106: 422651518 | L106: 467435702 | M106: 466882184 | N106: 518018762 | O106: 504142392 | P106: 132760018
A107: +Perdidas por deterioro de valor (reversiones de perdidas por deterioro de valor) reconocidas en el resultado del periodo | B107: -29542543 | C107: -38803907 | D107: -50830636 | E107: -52271691 | F107: -55250343 | G107: -53796077 | H107: -58901242 | I107: -52089500 | J107: -68584398 | K107: -70132193 | L107: -79684088 | M107: -98585660 | N107: -106577967 | O107: -122085652 | P107: 22258555
A108: -Otros gastos, por naturaleza | B108: 503407491 | C108: 568806105 | D108: 716744150 | E108: 956136841 | F108: 1024171930 | G108: 1137592884 | H108: 1168814862 | I108: 1220664545 | J108: 1171742705 | K108: 1100674425 | L108: 1131313467 | M108: 1342942385 | N108: 1459378315 | O108: 1395401392 | P108: 380732041
A109: +Otras ganancias (perdidas) | B109: -1493117 | C109: -1456948 | D109: -122644 | E109: 2433477 | F109: 5981586 | G109: -33432 | H109: 390536 | I109: 124569 | J109: -89000 | K109: 207275453 | L109: 41585368 | M109: 20809511 | N109: 544963983 | O109: 51324376 | P109: -116948
A110: =Ganancias (perdidas) de actividades operacionales EBIT | B110: 208540723 | C110: 238227340 | D110: 221580037 | E110: 218036930 | F110: 126769297 | G110: 80843799 | H110: 114395321 | I110: 117385336 | J110: 90913071 | K110: 343916569 | L110: 212469036 | M110: 294374685 | N110: 757608676 | O110: 249569340 | P110: 51836701
A111: +Ganancias (perdidas) que surgen de la baja en cuentas de activos financieros medidos al costo amortizado | B111: 0 | C111: 0 | D111: 0 | E111: 0 | F111: 0 | G111: 0 | H111: 0 | I111: 0 | J111: 0 | K111: 0 | L111: 0 | M111: 0 | N111: 0 | O111: 0 | P111: 0
A112: +Ingresos financieros | B112: 970282 | C112: 3059293 | D112: 2823225 | E112: 1946886 | F112: 10818705 | G112: 12183865 | H112: 5952920 | I112: 5225532 | J112: 1889772 | K112: 8746947 | L112: 10894534 | M112: 4919952 | N112: 26563887 | O112: 26535094 | P112: 11361421
A113: -Costos financieros | B113: 9900811 | C113: 10315663 | D113: 13700677 | E113: 20838218 | F113: 55252785 | G113: 70978326 | H113: 82221963 | I113: 80035968 | J113: 77711185 | K113: 97558997 | L113: 102535938 | M113: 113951133 | N113: 113696383 | O113: 113270200 | P113: 27500891
A114: +Deterioro de valor de ganancias y reversion de perdidas por deterioro de valor (perdidas por deterioro de valor) determinado de acuerdo con la NIIF 9 | B114: - | C114: 0 | D114: 0 | E114: 0 | F114: 0 | G114: 0 | H114: 0 | I114: 0 | J114: 0 | K114: 0 | L114: 0 | M114: 0 | N114: 0 | O114: 0 | P114: 0
A115: +Participacion en las ganancias (perdidas) de asociadas y negocios conjuntos que se contabilicen utilizando el metodo de la participacion | B115: 0 | C115: 0 | D115: 0 | E115: 0 | F115: 0 | G115: 0 | H115: 0 | I115: 0 | J115: 0 | K115: 0 | L115: 0 | M115: 0 | N115: 0 | O115: 0 | P115: 0
A116: +Diferencias de cambio | B116: 1296277 | C116: -6349377 | D116: -8795595 | E116: -21078202 | F116: -11243068 | G116: -12945839 | H116: -16051379 | I116: -6973571 | J116: -994222 | K116: 4551310 | L116: -115094 | M116: 250185 | N116: -350491 | O116: -3187775 | P116: -1343755
A117: +Resultados por unidades de reajuste | B117: -3337075 | C117: -5295078 | D117: -3270641 | E117: -1150441 | F117: -22635632 | G117: -22985872 | H117: -15934835 | I117: -9600405 | J117: -16368412 | K117: -19445992 | L117: -26758482 | M117: -66963329 | N117: -130374245 | O117: -39051828 | P117: -5147068
A118: +Ganancias (perdidas) que surgen de diferencias entre importes en libros anteriores y el valor razonable de activos financieros reclasificados como medidos al valor razonable | B118: 0 | C118: 0 | D118: 0 | E118: 0 | F118: 0 | G118: 0 | H118: 0 | I118: 0 | J118: 0 | K118: 0 | L118: 0 | M118: 0 | N118: 0 | O118: 0 | P118: 0
A119: +Gan (perd) acum anteriormente recon en otro res integral que surge de la reclas de act fin de la categoria de medicion de vl raz con cambios en otro res int a la de vl raz con cambios en res | B119: - | C119: 0 | D119: 0 | E119: 0 | F119: 0 | G119: 0 | H119: 0 | I119: 0 | J119: 0 | K119: 0 | L119: 0 | M119: 0 | N119: 0 | O119: 0 | P119: 0
...

Sheet Análisis
A1: LIQUIDEZ
B2: 2010 | C2: 2011 | D2: 2012 | E2: 2013 | F2: 2014 | G2: 2015 | H2: 2016 | I2: 2017 | J2: 2018 | K2: 2019 | L2: 2020 | M2: 2021 | N2: 2022 | O2: 2023
A3: Razón Corriente | B3: =ENEL!B4/ENEL!B34 -> 1.008782 | C3: =ENEL!C4/ENEL!C34 -> 0.9276463 | D3: =ENEL!D4/ENEL!D34 -> 0.9624764 | E3: =ENEL!E4/ENEL!E34 -> 1.1028869 | F3: =ENEL!F4/ENEL!F34 -> 1.5031731 | G3: =ENEL!G4/ENEL!G34 -> 1.186718 | H3: =ENEL!H4/ENEL!H34 -> 1.3330373 | I3: =ENEL!I4/ENEL!I34 -> 1.1949635 | ... O3: =ENEL!O4/ENEL!O34 -> 1.1937721
A4: Liquidez Real | B4: =(ENEL!B4-(ENEL!B11+ENEL!B12 + ENEL!B13))/ENEL!B34 -> 0.8655524 | C4: =(ENEL!C4-(ENEL!C11+ENEL!C12 + ENEL!C13))/ENEL!C34 -> 0.7537589 | D4: =(ENEL!D4-(ENEL!D11+ENEL!D12 + ENEL!D13))/ENEL!D34 -> 0.79257689 | E4: =(ENEL!E4-(ENEL!E11+ENEL!E12 + ENEL!E13))/ENEL!E34 -> 0.74179234 | F4: =(ENEL!F4-(ENEL!F11+ENEL!F12 + ENEL!F13))/ENEL!F34 -> 1.2311652 | G4: =(ENEL!G4-(ENEL!G11+ENEL!G12 + ENEL!G13))/ENEL!G34 -> 0.84961386 | H4: =(ENEL!H4-(ENEL!H11+ENEL!H12 + ENEL!H13))/ENEL!H34 -> 0.82604372 | I4: =(ENEL!I4-(ENEL!I11+ENEL!I12 + ENEL!I13))/ENEL!I34 -> 0.84797178 | ... O4: =(ENEL!O4-(ENEL!O11+ENEL!O12 + ENEL!O13))/ENEL!O34 -> 1.0932569
A5: Prueba Ácida | B5: =(ENEL!B4-ENEL!B11)/ENEL!B34 -> 0.91100835 | C5: =(ENEL!C4-ENEL!C11)/ENEL!C34 -> 0.76762101 | D5: =(ENEL!D4-ENEL!D11)/ENEL!D34 -> 0.81143055 | E5: =(ENEL!E4-ENEL!E11)/ENEL!E34 -> 0.81089035 | F5: =(ENEL!F4-ENEL!F11)/ENEL!F34 -> 1.3204922 | G5: =(ENEL!G4-ENEL!G11)/ENEL!G34 -> 1.0252984 | H5: =(ENEL!H4-ENEL!H11)/ENEL!H34 -> 1.1743419 | I5: =(ENEL!I4-ENEL!I11)/ENEL!I34 -> 1.0394805 | ... O5: =(ENEL!O4-ENEL!O11)/ENEL!O34 -> 1.1133338
A26: ENDEUDAMIENTO
A27: Año | B27: 2010 | C27: 2011 | D27: 2012 | E27: 2013 | F27: 2014 | G27: 2015 | H27: 2016 | I27: 2017 | J27: 2018 | K27: 2019 | L27: 2020 | M27: 2021 | N27: 2022 | O27: 2023
A28: Razón de Deuda | B28: =ENEL!B33/ENEL!B3 -> 0.51562006 | C28: =ENEL!C33/ENEL!C3 -> 0.50380607 | D28: =ENEL!D33/ENEL!D3 -> 0.51983246 | E28: =ENEL!E33/ENEL!E3 -> 0.60961248 | F28: =ENEL!F33/ENEL!F3 -> 0.68497717 | G28: =ENEL!G33/ENEL!G3 -> 0.70721405 | H28: =ENEL!H33/ENEL!H3 -> 0.63743868 | I28: =ENEL!I33/ENEL!I3 -> 0.64909689 | ... O28: =ENEL!O33/ENEL!O3 -> 0.7059932
A29: Razón Deuda CP | B29: =ENEL!B34/ENEL!B3 -> 0.25272129 | C29: =ENEL!C34/ENEL!C3 -> 0.25305385 | D29: =ENEL!D34/ENEL!D3 -> 0.25914843 | E29: =ENEL!E34/ENEL!E3 -> 0.22830384 | F29: =ENEL!F34/ENEL!F3 -> 0.19315754 | G29: =ENEL!G34/ENEL!G3 -> 0.17929409 | H29: =ENEL!H34/ENEL!H3 -> 0.16551111 | I29: =ENEL!I34/ENEL!I3 -> 0.17664995 | ... O29: =ENEL!O34/ENEL!O3 -> 0.23461414
A30: Leverage Financiero | B30: =ENEL!B33/ENEL!B56 -> 1.0644951 | C30: =ENEL!C33/ENEL!C56 -> 1.0153411 | D30: =ENEL!D33/ENEL!D56 -> 1.0826064 | E30: =ENEL!E33/ENEL!E56 -> 1.5615573 | F30: =ENEL!F33/ENEL!F56 -> 2.1743731 | G30: =ENEL!G33/ENEL!G56 -> 2.4154645 | H30: =ENEL!H33/ENEL!H56 -> 1.7581541 | I30: =ENEL!I33/ENEL!I56 -> 1.8497895 | ... O30: =ENEL!O33/ENEL!O56 -> 2.4012818
A31: Cobertura Total | B31: 1.4284511 | C31: 1.5993465 | D31: 1.4804265 | E31: 1.0160561 | F31: 0.68221925 | G31: 0.64504753 | H31: 0.76089466 | I31: 0.758164 | J31: 0.75317701 | K31: 1.0044206 | L31: 0.97205794 | M31: 0.92775907 | N31: 1.5807347 | O31: 0.95091404
A32: Cobertura G.F. | B32: =(ENEL!B128+ENEL!B113)/ENEL!B113 -> 18.470408 | C32: =(ENEL!C128+ENEL!C113)/ENEL!C113 -> 18.523513 | D32: =(ENEL!D128+ENEL!D113)/ENEL!D113 -> 13.210646 | E32: =(ENEL!E128+ENEL!E113)/ENEL!E113 -> 8.0526786 | F32: =(ENEL!F128+ENEL!F113)/ENEL!F113 -> 2.022039 | G32: =(ENEL!G128+ENEL!G113)/ENEL!G113 -> 0.98447418 | H32: =(ENEL!H128+ENEL!H113)/ENEL!H113 -> 1.4154377 | I32: =(ENEL!I128+ENEL!I113)/ENEL!I113 -> 1.5423754 | ... O32: =(ENEL!O128+ENEL!O113)/ENEL!O113 -> 1.7847109
A33: COBERTURA
B34: 2010 | C34: 2011 | D34: 2012 | E34: 2013 | F34: 2014 | G34: 2015 | H34: 2016 | I34: 2017 | J34: 2018 | K34: 2019 | L34: 2020 | M34: 2021 | N34: 2022 | O34: 2023 | P34: 2024
A36: Cobertura Total | B36: =(ENEL!B128+ENEL!B113+ENEL!B122+ENEL!B106-ENEL!B107)/(ENEL!B113+ENEL!B38) -> 1.4284511 | C36: =(ENEL!C128+ENEL!C113+ENEL!C122+ENEL!C106-ENEL!C107)/(ENEL!C113+ENEL!C38) -> 1.5993465 | D36: =(ENEL!D128+ENEL!D113+ENEL!D122+ENEL!D106-ENEL!D107)/(ENEL!D113+ENEL!D38) -> 1.4804265 | E36: =(ENEL!E128+ENEL!E113+ENEL!E122+ENEL!E106-ENEL!E107)/(ENEL!E113+ENEL!E38) -> 1.0160561 | F36: =(ENEL!F128+ENEL!F113+ENEL!F122+ENEL!F106-ENEL!F107)/(ENEL!F113+ENEL!F38) -> 0.68221925 | G36: =(ENEL!G128+ENEL!G113+ENEL!G122+ENEL!G106-ENEL!G107)/(ENEL!G113+ENEL!G38) -> 0.64504753 | H36: =(ENEL!H128+ENEL!H113+ENEL!H122+ENEL!H106-ENEL!H107)/(ENEL!H113+ENEL!H38) -> 0.76089466 | I36: =(ENEL!I128+ENEL!I113+ENEL!I122+ENEL!I106-ENEL!I107)/(ENEL!I113+ENEL!I38) -> 0.758164 | ... P36: =(ENEL!P128+ENEL!P113+ENEL!P122+ENEL!P106-ENEL!P107)/(ENEL!P113+ENEL!P38) -> 0.2132231
L44: Ok normal
A56: EFICIENCIA
B57: 2010 | C57: 2011 | D57: 2012 | E57: 2013 | F57: 2014 | G57: 2015 | H57: 2016 | I57: 2017 | J57: 2018 | K57: 2019 | L57: 2020 | M57: 2021 | N57: 2022 | O57: 2023 | P57: 2024
L67: por qué? | M67: inv de act o - ixv
L68: aumento de activos
A81: RENTABILIDAD
A82: Año | B82: 2010 | C82: 2011 | D82: 2012 | E82: 2013 | F82: 2014 | G82: 2015 | H82: 2016 | I82: 2017 | J82: 2018 | K82: 2019 | L82: 2020 | M82: 2021 | N82: 2022 | O82: 2023
A83: Rotación de Activos | B83: =ENEL!B100/ENEL!B3 -> 0.72759951 | C83: =ENEL!C100/ENEL!C3 -> 0.78997894 | D83: =ENEL!D100/ENEL!D3 -> 0.84359906 | E83: =ENEL!E100/ENEL!E3 -> 0.72149383 | F83: =ENEL!F100/ENEL!F3 -> 0.54129715 | G83: =ENEL!G100/ENEL!G3 -> 0.54693172 | H83: =ENEL!H100/ENEL!H3 -> 0.53662678 | I83: =ENEL!I100/ENEL!I3 -> 0.55059481 | ... O83: =ENEL!O100/ENEL!O3 -> 0.43408104
A84: Margen Operacional | B84: =(ENEL!B100-ENEL!B105-ENEL!B108)/ENEL!B100 -> 0.43195256 | C84: =(ENEL!C100-ENEL!C105-ENEL!C108)/ENEL!C100 -> 0.43606978 | D84: =(ENEL!D100-ENEL!D105-ENEL!D108)/ENEL!D100 -> 0.39970055 | E84: =(ENEL!E100-ENEL!E105-ENEL!E108)/ENEL!E100 -> 0.30700561 | F84: =(ENEL!F100-ENEL!F105-ENEL!F108)/ENEL!F100 -> 0.24151309 | G84: =(ENEL!G100-ENEL!G105-ENEL!G108)/ENEL!G100 -> 0.22414614 | H84: =(ENEL!H100-ENEL!H105-ENEL!H108)/ENEL!H100 -> 0.24269254 | I84: =(ENEL!I100-ENEL!I105-ENEL!I108)/ENEL!I100 -> 0.24355417 | ... O84: =(ENEL!O100-ENEL!O105-ENEL!O108)/ENEL!O100 -> 0.31384169
A85: Margen Neto | B85: =ENEL!B128/ENEL!B100 -> 0.15962715 | C85: =ENEL!C128/ENEL!C100 -> 0.14686945 | D85: =ENEL!D128/ENEL!D100 -> 0.11697943 | E85: =ENEL!E128/ENEL!E100 -> 0.09025268 | F85: =ENEL!F128/ENEL!F100 -> 0.034364768 | G85: =ENEL!G128/ENEL!G100 -> -0.00061749926 | H85: =ENEL!H128/ENEL!H100 -> 0.018288887 | I85: =ENEL!I128/ENEL!I100 -> 0.022340685 | ... O85: =ENEL!O128/ENEL!O100 -> 0.03593186
A86: ROA | B86: =B85*B83 -> 0.11614464 | C86: =C85*C83 -> 0.11602377 | D86: =D85*D83 -> 0.098683735 | E86: =E85*E83 -> 0.065116752 | F86: =F85*F83 -> 0.018601551 | G86: =G85*G83 -> -0.00033772993 | H86: =H85*H83 -> 0.0098143064 | I86: =I85*I83 -> 0.012300665 | ... O86: =O85*O83 -> 0.015597339
A87: ROA(2) | B87: =(ENEL!B121+ENEL!B113)/ENEL!B3 -> 0.13930961 | C87: =(ENEL!C121+ENEL!C113)/ENEL!C3 -> 0.14739417 | D87: =(ENEL!D121+ENEL!D113)/ENEL!D3 -> 0.12525372 | E87: =(ENEL!E121+ENEL!E113)/ENEL!E3 -> 0.087620538 | F87: =(ENEL!F121+ENEL!F113)/ENEL!F3 -> 0.034162151 | G87: =(ENEL!G121+ENEL!G113)/ENEL!G3 -> 0.017498244 | H87: =(ENEL!H121+ENEL!H113)/ENEL!H3 -> 0.02538818 | I87: =(ENEL!I121+ENEL!I113)/ENEL!I3 -> 0.03004695 | ... O87: =(ENEL!O121+ENEL!O113)/ENEL!O3 -> 0.041038366
A88: ROA(3) | B88: =(ENEL!B121+ENEL!B113+ENEL!B106)/ENEL!B3 -> 0.29589561 | C88: =(ENEL!C121+ENEL!C113+ENEL!C106)/ENEL!C3 -> 0.32056249 | D88: =(ENEL!D121+ENEL!D113+ENEL!D106)/ENEL!D3 -> 0.30815834 | E88: =(ENEL!E121+ENEL!E113+ENEL!E106)/ENEL!E3 -> 0.19624764 | F88: =(ENEL!F121+ENEL!F113+ENEL!F106)/ENEL!F3 -> 0.11309872 | G88: =(ENEL!G121+ENEL!G113+ENEL!G106)/ENEL!G3 -> 0.10135647 | H88: =(ENEL!H121+ENEL!H113+ENEL!H106)/ENEL!H3 -> 0.11146476 | I88: =(ENEL!I121+ENEL!I113+ENEL!I106)/ENEL!I3 -> 0.11955221 | ... O88: =(ENEL!O121+ENEL!O113+ENEL!O106)/ENEL!O3 -> 0.12950477
A89: ROE | B89: =B86/(1-B28) -> 0.23978004 | C89: =C86/(1-C28) -> 0.23382747 | D89: =D86/(1-D28) -> 0.20551938 | E89: =E86/(1-E28) -> 0.16680029 | F89: =F86/(1-F28) -> 0.059048262 | G89: =G86/(1-G28) -> -0.0011535046 | H89: =H86/(1-H28) -> 0.02706937 | I89: =I86/(1-I28) -> 0.035054306 | ... O89: =O86/(1-O28) -> 0.053050947
O96: por qué disminuyo?
O97: por qué la brecha disminuye y dsps aumenta
O100: sciencedirect.com
O101: GARCH
C107: y esa subida? | I107: esa subida?
C108: ganancias extraordinarias | I108: ganancias extraordinarias
A111: Margen Op 2 | B111: =(ENEL!B110+IF(ENEL!B109<0, -ENEL!B109, ENEL!B109) -ENEL!B107 +ENEL!B106)/ENEL!B100 -> 0.43630304 | C111: =(ENEL!C110+IF(ENEL!C109<0, -ENEL!C109, ENEL!C109) -ENEL!C107 +ENEL!C106)/ENEL!C100 -> 0.44547258 | D111: =(ENEL!D110+IF(ENEL!D109<0, -ENEL!D109, ENEL!D109) -ENEL!D107 +ENEL!D106)/ENEL!D100 -> 0.40738194 | E111: =(ENEL!E110+IF(ENEL!E109<0, -ENEL!E109, ENEL!E109) -ENEL!E107 +ENEL!E106)/ENEL!E100 -> 0.31805197 | F111: =(ENEL!F110+IF(ENEL!F109<0, -ENEL!F109, ENEL!F109) -ENEL!F107 +ENEL!F106)/ENEL!F100 -> 0.26023549 | G111: =(ENEL!G110+IF(ENEL!G109<0, -ENEL!G109, ENEL!G109) -ENEL!G107 +ENEL!G106)/ENEL!G100 -> 0.22878846 | H111: =(ENEL!H110+IF(ENEL!H109<0, -ENEL!H109, ENEL!H109) -ENEL!H107 +ENEL!H106)/ENEL!H100 -> 0.25339838 | I111: =(ENEL!I110+IF(ENEL!I109<0, -ENEL!I109, ENEL!I109) -ENEL!I107 +ENEL!I106)/ENEL!I100 -> 0.24984522 | ... O111: =(ENEL!O110+IF(ENEL!O109<0, -ENEL!O109, ENEL!O109) -ENEL!O107 +ENEL!O106)/ENEL!O100 -> 0.37479268
A114: VALORES EN LIBRO
A115: UDI | B115: =ENEL!B128 -> 172971209 | C115: =ENEL!C128 -> 180766659 | D115: =ENEL!D128 -> 167294116 | E115: =ENEL!E128 -> 146965254 | F115: =ENEL!F128 -> 56470502 | G115: =ENEL!G128 -> -1101997 | H115: =ENEL!H128 -> 34158100 | I115: =ENEL!I128 -> 43409541 | ... P115: =ENEL!P128 -> -20431517
A116: EVA | B116: =ENEL!B128-ENEL!B113-ENEL!B109 -> 164563515 | C116: =ENEL!C128-ENEL!C113-ENEL!C109 -> 171907944 | D116: =ENEL!D128-ENEL!D113-ENEL!D109 -> 153716083 | E116: =ENEL!E128-ENEL!E113-ENEL!E109 -> 123693559 | F116: =ENEL!F128-ENEL!F113-ENEL!F109 -> -4763869 | G116: =ENEL!G128-ENEL!G113-ENEL!G109 -> -72046891 | H116: =ENEL!H128-ENEL!H113-ENEL!H109 -> -48454399 | I116: =ENEL!I128-ENEL!I113-ENEL!I109 -> -36750996 | ... P116: =ENEL!P128-ENEL!P113-ENEL!P109 -> -47815460
B118: 2010 | C118: 2011 | D118: 2012 | E118: 2013 | F118: 2014 | G118: 2015 | H118: 2016 | I118: 2017 | J118: 2018 | K118: 2019 | L118: 2020 | M118: 2021 | N118: 2022 | O118: 2023 | P118: 2024
A119: IPC a 2024 | B119: 0.749 | C119: 0.675 | D119: 0.65 | E119: 0.602 | F119: 0.531 | G119: 0.467 | H119: 0.428 | I119: 0.396 | J119: 0.362 | K119: 0.322 | L119: 0.284 | M119: 0.198 | N119: 0.062 | O119: 0.022 | P119: 0.005
A121: VALORES PRESENTES
A122: UDI | B122: =B115*(1+B119) -> 3.0252664e+08 | C122: =C115*(1+C119) -> 3.0278415e+08 | D122: =D115*(1+D119) -> 2.7603529e+08 | E122: =E115*(1+E119) -> 2.3543834e+08 | F122: =F115*(1+F119) -> 86456339 | G122: =G115*(1+G119) -> -1616629.6 | H122: =H115*(1+H119) -> 48777767 | I122: =I115*(1+I119) -> 60599719 | ... P122: =P115*(1+P119) -> -20533675
A123: EVA | B123: =B116*(1+B119) -> 2.8782159e+08 | C123: =C116*(1+C119) -> 2.8794581e+08 | D123: =D116*(1+D119) -> 2.5363154e+08 | E123: =E116*(1+E119) -> 1.9815708e+08 | F123: =F116*(1+F119) -> -7293483.4 | G123: =G116*(1+G119) -> -1.0569279e+08 | H123: =H116*(1+H119) -> -69192882 | I123: =I116*(1+I119) -> -51304390 | ... P123: =P116*(1+P119) -> -48054537
A145: ESTRUCTURA DE CAPITAL DE TRABAJO
B146: 2010 | E146: 2013 | H146: 2016 | K146: 2019 | N146: 2022
A147: ACTIVOS | B147: =ENEL!B3 -> 1489274149 | C147: =ENEL!C3 -> 1558014006 | D147: =ENEL!D3 -> 1695255205 | E147: =ENEL!E3 -> 2256949998 | F147: =ENEL!F3 -> 3035795403 | G147: =ENEL!G3 -> 3262953316 | H147: =ENEL!H3 -> 3480439534 | I147: =ENEL!I3 -> 3529040173 | ... O147: =ENEL!O3 -> 5698687722
A148: ACTIVOS CORRIENTES | B148: =ENEL!B4 -> 379676583 | C148: =ENEL!C4 -> 365735174 | D148: =ENEL!D4 -> 422837752 | E148: =ENEL!E4 -> 568284929 | F148: =ENEL!F4 -> 881440823 | G148: =ENEL!G4 -> 694263548 | H148: =ENEL!H4 -> 767898036 | I148: =ENEL!I4 -> 744945928 | ... O148: =ENEL!O4 -> 1596064579
A149: ACTIVOS NO CORRIENTES | B149: =ENEL!B14 -> 1109597566 | C149: =ENEL!C14 -> 1192278832 | D149: =ENEL!D14 -> 1272417453 | E149: =ENEL!E14 -> 1688665069 | F149: =ENEL!F14 -> 2154354580 | G149: =ENEL!G14 -> 2568689768 | H149: =ENEL!H14 -> 2712541498 | I149: =ENEL!I14 -> 2784094245 | ... O149: =ENEL!O14 -> 4102623143
A151: PASIVO | B151: =ENEL!B33 -> 767899626 | C151: =ENEL!C33 -> 784936915 | D151: =ENEL!D33 -> 881248684 | E151: =ENEL!E33 -> 1375864886 | F151: =ENEL!F33 -> 2079450541 | G151: =ENEL!G33 -> 2307606436 | H151: =ENEL!H33 -> 2218566793 | I151: =ENEL!I33 -> 2290689003 | ... O151: =ENEL!O33 -> 4023234762
A152: PASIVO CORRIENTE | B152: =ENEL!B34 -> 376371289 | C152: =ENEL!C34 -> 394261450 | D152: =ENEL!D34 -> 439322720 | E152: =ENEL!E34 -> 515270360 | F152: =ENEL!F34 -> 586386773 | G152: =ENEL!G34 -> 585028258 | H152: =ENEL!H34 -> 576051414 | I152: =ENEL!I34 -> 623404767 | ... O152: =ENEL!O34 -> 1336992696
A153: PASIVO NO CORRIENTE | B153: =ENEL!B45 -> 391528337 | C153: =ENEL!C45 -> 390675465 | D153: =ENEL!D45 -> 441925964 | E153: =ENEL!E45 -> 860594526 | F153: =ENEL!F45 -> 1493063768 | G153: =ENEL!G45 -> 1722578178 | H153: =ENEL!H45 -> 1642515379 | I153: =ENEL!I45 -> 1667284236 | ... O153: =ENEL!O45 -> 2686242066
A154: PATRIMONIO | B154: =ENEL!B56 -> 721374523 | C154: =ENEL!C56 -> 773077091 | D154: =ENEL!D56 -> 814006521 | E154: =ENEL!E56 -> 881085112 | F154: =ENEL!F56 -> 956344862 | G154: =ENEL!G56 -> 955346880 | H154: =ENEL!H56 -> 1261872741 | I154: =ENEL!I56 -> 1238351170 | ... O154: =ENEL!O56 -> 1675452960
B157: Equilibrada | C157: Agresiva | D157: Agresiva | E157: Conservadora | F157: Conservadora | G157: Conservadora | H157: Conservadora | I157: Conservadora | J157: Conservadora | K157: Conservadora | L157: Conservadora | M157: Conservadora | N157: Conservadora | O157: Conservadora
C158: ojo con la cobertura en estos casos
A160: PROPORCIÓN DEL ACTIVO
B161: 2010 | E161: 2013 | H161: 2016 | K161: 2019 | N161: 2022
A162: ANC/AT | B162: =B149/B147 -> 0.74505931 | C162: =C149/C147 -> 0.76525553 | D162: =D149/D147 -> 0.75057575 | E162: =E149/E147 -> 0.74820668 | F162: =F149/F147 -> 0.70965078 | G162: =G149/G147 -> 0.78722848 | H162: =H149/H147 -> 0.77936751 | I162: =I149/I147 -> 0.78890976 | ... O162: =O149/O147 -> 0.71992419
A163: AC/AT | B163: =B148/B147 -> 0.25494069 | C163: =C148/C147 -> 0.23474447 | D163: =D148/D147 -> 0.24942425 | E163: =E148/E147 -> 0.25179332 | F163: =F148/F147 -> 0.29034922 | G163: =G148/G147 -> 0.21277152 | H163: =H148/H147 -> 0.22063249 | I163: =I148/I147 -> 0.21109024 | ... O163: =O148/O147 -> 0.28007581

Sheet A plotear
B2: Ratio\Año | C2: 2010 | D2: 2011 | E2: 2012 | F2: 2013 | G2: 2014 | H2: 2015 | I2: 2016 | J2: 2017 | K2: 2018 | L2: 2019 | M2: 2020 | N2: 2021 | O2: 2022 | P2: 2023
B3: Razón Corriente | C3: 1.008782 | D3: 0.9276463 | E3: 0.9624764 | F3: 1.1028869 | G3: 1.5031731 | H3: 1.186718 | I3: 1.3330373 | J3: 1.1949635 | K3: 1.2305196 | L3: 1.5153546 | M3: 1.69127 | N3: 1.1189109 | O3: 1.311502 | P3: 1.1937721
B4: Liquidez Real | C4: 0.8655524 | D4: 0.7537589 | E4: 0.79257689 | F4: 0.74179234 | G4: 1.2311652 | H4: 0.84961386 | I4: 0.82604372 | J4: 0.84797178 | K4: 0.96845905 | L4: 1.3553248 | M4: 1.4337304 | N4: 0.99302051 | O4: 0.97900694 | P4: 1.0932569
B5: Prueba Ácida | C5: 0.91100835 | D5: 0.76762101 | E5: 0.81143055 | F5: 0.81089035 | G5: 1.3204922 | H5: 1.0252984 | I5: 1.1743419 | J5: 1.0394805 | K5: 1.0480058 | L5: 1.422633 | M5: 1.5957892 | N5: 1.0144468 | O5: 1.205107 | P5: 1.1133338
B10: Ratio\Año | C10: 2010 | D10: 2011 | E10: 2012 | F10: 2013 | G10: 2014 | H10: 2015 | I10: 2016 | J10: 2017 | K10: 2018 | L10: 2019 | M10: 2020 | N10: 2021 | O10: 2022 | P10: 2023
B11: Razón de Deuda | C11: 0.51562006 | D11: 0.50380607 | E11: 0.51983246 | F11: 0.60961248 | G11: 0.68497717 | H11: 0.70721405 | I11: 0.63743868 | J11: 0.64909689 | K11: 0.65531086 | L11: 0.68881393 | M11: 0.69141709 | N11: 0.72259468 | O11: 0.72217703 | P11: 0.7059932
B12: Razón Deuda CP | C12: 0.25272129 | D12: 0.25305385 | E12: 0.25914843 | F12: 0.22830384 | G12: 0.19315754 | H12: 0.17929409 | I12: 0.16551111 | J12: 0.17664995 | K12: 0.16617234 | L12: 0.17235759 | M12: 0.16654721 | N12: 0.21400028 | O12: 0.20231456 | P12: 0.23461414
B13: Leverage Financiero | C13: 1.0644951 | D13: 1.0153411 | E13: 1.0826064 | F13: 1.5615573 | G13: 2.1743731 | H13: 2.4154645 | I13: 1.7581541 | J13: 1.8497895 | K13: 1.9011648 | L13: 2.2135115 | M13: 2.2406202 | N13: 2.6048336 | O13: 2.5994144 | P13: 2.4012818
B14: Cobertura Total | C14: 1.4284511 | D14: 1.5993465 | E14: 1.4804265 | F14: 1.0160561 | G14: 0.68221925 | H14: 0.64504753 | I14: 0.76089466 | J14: 0.758164 | K14: 0.75317701 | L14: 1.0044206 | M14: 0.97205794 | N14: 0.92775907 | O14: 1.5807347 | P14: 0.95091404
B15: Cobertura G.F. | C15: 18.470408 | D15: 18.523513 | E15: 13.210646 | F15: 8.0526786 | G15: 2.022039 | H15: 0.98447418 | I15: 1.4154377 | J15: 1.5423754 | K15: 0.69613007 | L15: 2.5800911 | M15: 1.8237721 | N15: 1.6579602 | O15: 5.0176065 | P15: 1.7847109
B18: Ratio\Año | C18: 2010 | D18: 2011 | E18: 2012 | F18: 2013 | G18: 2014 | H18: 2015 | I18: 2016 | J18: 2017 | K18: 2018 | L18: 2019 | M18: 2020 | N18: 2021 | O18: 2022 | P18: 2023
B19: Rotación de Activos | C19: 0.72759951 | D19: 0.78997894 | E19: 0.84359906 | F19: 0.72149383 | G19: 0.54129715 | H19: 0.54693172 | I19: 0.53662678 | J19: 0.55059481 | K19: 0.4826111 | L19: 0.38278256 | M19: 0.42807977 | N19: 0.44797312 | O19: 0.45407071 | P19: 0.43408104
... B25: ROE | C25: 0.23978004 | D25: 0.23382747 | E25: 0.20551938 | F25: 0.16680029 | G25: 0.059048262 | H25: -0.0011535046 | I25: 0.02706937 | J25: 0.035054306 | K25: -0.017281698 | L25: 0.095825548 | M25: 0.055993891 | N25: 0.049882267 | O25: 0.29384541 | P25: 0.053050947
C31: 2010 | D31: 2011 | E31: 2012 | F31: 2013 | G31: 2014 | H31: 2015 | I31: 2016 | J31: 2017 | K31: 2018 | L31: 2019 | M31: 2020 | N31: 2021 | O31: 2022 | P31: 2023
B32: Ingresos por Venta | C32: 1083595141 | D32: 1230798252 | E32: 1430115702 | F32: 1628375505 | G32: 1643267385 | H32: 1784612663 | I32: 1867697070 | J32: 1943071198 | K32: 1913174282 | L32: 1978791988 | M32: 2092644232 | N32: 2427220678 | O32: 2540682904 | P32: 2473692310
B33: IxV con IPC | C33: =C32*(1+Análisis!B119) -> 1.8952079e+09 | D33: =D32*(1+Análisis!C119) -> 2.0615871e+09 | E33: =E32*(1+Análisis!D119) -> 2.3596909e+09 | F33: =F32*(1+Análisis!E119) -> 2.6086576e+09 | G33: =G32*(1+Análisis!F119) -> 2.5158424e+09 | H33: =H32*(1+Análisis!G119) -> 2.6180268e+09 | I33: =I32*(1+Análisis!H119) -> 2.6670714e+09 | J33: =J32*(1+Análisis!I119) -> 2.7125274e+09 | ... P33: =P32*(1+Análisis!O119) -> 2.5281135e+09
C38: 2010 | D38: 2011 | E38: 2012 | F38: 2013 | G38: 2014 | H38: 2015 | I38: 2016 | J38: 2017 | K38: 2018 | L38: 2019 | M38: 2020 | N38: 2021 | O38: 2022 | P38: 2023
B39: Patrimonio neto | C39: 721374523 | D39: 773077091 | E39: 814006521 | F39: 881085112 | G39: 956344862 | H39: 955346880 | I39: 1261872741 | J39: 1238351170 | K39: 1366421962 | L39: 1608674398 | M39: 1508490427 | N39: 1503045367 | O39: 1554515776 | P39: 1675452960
B40: =Ganancia (perdida) neta | C40: 172971209 | D40: 180766659 | E40: 167294116 | F40: 146965254 | G40: 56470502 | H40: -1101997 | I40: 34158100 | J40: 43409541 | K40: -23614092 | L40: 154152106 | M40: 84466248 | N40: 74975311 | O40: 456787332 | P40: 88884366
B41: ROE | C41: =C40/C39 -> 0.23978004 | D41: =D40/D39 -> 0.23382747 | E41: =E40/E39 -> 0.20551938 | F41: =F40/F39 -> 0.16680029 | G41: =G40/G39 -> 0.059048262 | H41: =H40/H39 -> -0.0011535046 | I41: =I40/I39 -> 0.02706937 | J41: =J40/J39 -> 0.035054306 | ... P41: =P40/P39 -> 0.053050947
B61: Indice\Año | C61: 2010 | D61: 2011 | E61: 2012 | F61: 2013 | G61: 2014 | H61: 2015 | I61: 2016 | J61: 2017 | K61: 2018 | L61: 2019 | M61: 2020 | N61: 2021 | O61: 2022 | P61: 2023
B62: UDI | C62: 172971209 | D62: 180766659 | E62: 167294116 | F62: 146965254 | G62: 56470502 | H62: -1101997 | I62: 34158100 | J62: 43409541 | K62: -23614092 | L62: 154152106 | M62: 84466248 | N62: 74975311 | O62: 456787332 | P62: 88884366
B63: EVA | C63: 164563515 | D63: 171907944 | E63: 153716083 | F63: 123693559 | G63: -4763869 | H63: -72046891 | I63: -48454399 | J63: -36750996 | K63: -101236277 | L63: -150682344 | M63: -59655058 | N63: -59785333 | O63: -201873034 | P63: -75710210
B65: Indice con IPC\IPC | C65: 0.749 | D65: 0.675 | E65: 0.65 | F65: 0.602 | G65: 0.531 | H65: 0.467 | I65: 0.428 | J65: 0.396 | K65: 0.362 | L65: 0.322 | M65: 0.284 | N65: 0.198 | O65: 0.062 | P65: 0.022
B66: UDI c/IPC | C66: 3.0252664e+08 | D66: 3.0278415e+08 | E66: 2.7603529e+08 | F66: 2.3543834e+08 | G66: 86456339 | H66: -1616629.6 | I66: 48777767 | J66: 60599719 | K66: -32162393 | L66: 2.0378908e+08 | M66: 1.0845466e+08 | N66: 89820423 | O66: 4.8510815e+08 | P66: 90839822
B67: EVA c/IPC | C67: 2.8782159e+08 | D67: 2.8794581e+08 | E67: 2.5363154e+08 | F67: 1.9815708e+08 | G67: -7293483.4 | H67: -1.0569279e+08 | I67: -69192882 | J67: -51304390 | K67: -1.3788381e+08 | L67: -1.9920206e+08 | M67: -76597094 | N67: -71622829 | O67: -2.1438916e+08 | P67: -77375835
